ResoluteCNS/ResoluteCNS.py
ResoluteCNS/__init__.py
ResoluteCNS/uBlock0.xpi
ResoluteCNS/bankruptcies/__init__.py
ResoluteCNS/bankruptcies/bankruptcies.py
ResoluteCNS-0.2.6.dist-info/METADATA
ResoluteCNS-0.2.6.dist-info/WHEEL
ResoluteCNS-0.2.6.dist-info/top_level.txt
ResoluteCNS-0.2.6.dist-info/RECORD
