Metadata-Version: 2.1
Name: ResoluteCNS
Version: 0.2.6
Summary: CNS Scraping Package
Author: Ryan Detlaff
Author-email: rdetlaff@resolutecommercial.com
Keywords: python,first package
Classifier: Development Status :: 3 - Alpha
Classifier: Intended Audience :: Education
Classifier: Programming Language :: Python :: 2
Classifier: Programming Language :: Python :: 3
Classifier: Operating System :: MacOS :: MacOS X
Classifier: Operating System :: Microsoft :: Windows
Requires-Dist: selenium
Requires-Dist: pandas
